[[{"review_title": "Very much underpaid", "rating": "1.0", "reviewer_affiliation": "Former Employee", "job_date": "10 Jul 2016", "job_title": "Senior Financial Analyst in Miami, FL", "duration": "N/A", "pros": "able to do more work and learn more things", "cons": "no increase in pay, overworked, very strange culture"}, {"review_title": "Comcast is not a good company", "rating": "1.0", "reviewer_affiliation": "Former Employee, more than 1 year", "job_date": "16 Jan 2019", "job_title": "Sales Consultant", "duration": "N/A", "pros": "Good Pay. Awesome service, good benifits", "cons": "No advancement also the culture is horrible"}, {"review_title": "Worst Company Ever", "rating": "1.0", "reviewer_affiliation": "Current Employee", "job_date": "N/A", "job_title": "N/A", "duration": "N/A", "pros": "Benefits and Pay are good", "cons": "The way your treated and brought down everyday"}, {"review_title": "worst place to work", "rating": "1.0", "reviewer_affiliation": "Current Employee", "job_date": "N/A", "job_title": "N/A", "duration": "N/A", "pros": "free cable, commission is good", "cons": "the management sucks, even the customers hate comcast"}, {"review_title": "Horrible company to work for", "rating": "1.0", "reviewer_affiliation": "Current Employee", "job_date": "N/A", "job_title": "N/A", "duration": "N/A", "pros": "The people made it worth coming to work", "cons": "Management, micro managed the department"}, {"review_title": "Worst place ever to work", "rating": "1.0", "reviewer_affiliation": "Current Employee", "job_date": "N/A", "job_title": "N/A", "duration": "N/A", "pros": "You can be really lazy", "cons": "The whole organization is pretty much evil"}, {"review_title": "Technical Operations Manager", "rating": "1.0", "reviewer_affiliation": "Former Employee, more than 10 years", "job_date": "13 Apr 2015", "job_title": "Technical Operations Manager in Jacksonville, FL", "duration": "N/A", "pros": "Great health and welfare benefits", "cons": "Employees don't matter at the end of the day"}, {"review_title": "CEA", "rating": "1.0", "reviewer_affiliation": "Former Employee, more than 5 years", "job_date": "11 Jun 2015", "job_title": "Associate in Everett, WA", "duration": "N/A", "pros": "Great people to work with", "cons": "Part of ALEC, greed, no advancement, pay, does not value customers."}, {"review_title": "It's a job", "rating": "1.0", "reviewer_affiliation": "Current Employee", "job_date": "N/A", "job_title": "N/A", "duration": "N/A", "pros": "They pay you every 2 wks", "cons": "Everything else about the job"}, {"review_title": "sales rep 1", "rating": "1.0", "reviewer_affiliation": "Current Employee, less than 1 year", "job_date": "18 Apr 2016", "job_title": "Outbound Sales Representative in Atlanta, GA", "duration": "N/A", "pros": "Fun place cool people. great benefits thats about it", "cons": "High turn over and High sales demand"}], [{"review_title": "I dislike this company", "rating": "1.0", "reviewer_affiliation": "Former Employee", "job_date": "N/A", "job_title": "N/A", "duration": "N/A", "pros": "Please pay by the hour.", "cons": "Nice Co worker , I love them."}, {"review_title": "downhearted", "rating": "1.0", "reviewer_affiliation": "Former Employee", "job_date": "9 Jun 2016", "job_title": "FTC in Norcross, GA", "duration": "N/A", "pros": "terrible to employees no integrity or morality", "cons": "does not care about dedicated workers just another number"}, {"review_title": "master control", "rating": "1.0", "reviewer_affiliation": "Former Employee, more than 3 years", "job_date": "N/A", "job_title": "N/A", "duration": "N/A", "pros": "benefits are great   great staff party", "cons": "horrible management. little communication. hr doesn't support the staff"}, {"review_title": "account executive", "rating": "1.0", "reviewer_affiliation": "Former Employee", "job_date": "11 Mar 2017", "job_title": "Anonymous Employee", "duration": "N/A", "pros": "possibility of good pay and large company benefits. Good insurance", "cons": "poor treatment of customers and employees"}, {"review_title": "speed of downloading", "rating": "1.0", "reviewer_affiliation": "Current Employee", "job_date": "N/A", "job_title": "N/A", "duration": "N/A", "pros": "slowest internet in the world...easier to mail a letter", "cons": "slow as a snail  ..Horrible"}, {"review_title": "Horrible cut throat management", "rating": "1.0", "reviewer_affiliation": "Current Employee, more than 3 years", "job_date": "8 Oct 2017", "job_title": "Account Manager", "duration": "N/A", "pros": "Discounts on home cable service", "cons": "Almost everything!! Bad management, no direction"}, {"review_title": "Love lazy employees", "rating": "1.0", "reviewer_affiliation": "Former Employee, more than 10 years", "job_date": "21 Mar 2019", "job_title": "Tech", "duration": "N/A", "pros": "None. Bad management. Terrible team morale", "cons": "The lazier you are, the more they\u2019ll like you"}, {"review_title": "DO NOT MISS ANY TIME", "rating": "1.0", "reviewer_affiliation": "Former Employee, more than 3 years", "job_date": "7 Jul 2012", "job_title": "Anonymous Employee", "duration": "N/A", "pros": "free cable for the workers", "cons": "supervisors who don't know anything about their products"}, {"review_title": "Direct Sales Rep", "rating": "1.0", "reviewer_affiliation": "Former Employee, less than 1 year", "job_date": "22 Apr 2015", "job_title": "Direct Sales Representative in Mickleton, NJ", "duration": "N/A", "pros": "Worked with some good people", "cons": "To many to list. Not worth the time."}, {"review_title": "Downsizing", "rating": "1.0", "reviewer_affiliation": "Former Employee", "job_date": "N/A", "job_title": "N/A", "duration": "N/A", "pros": "Big Company, good benefits, decent salary", "cons": "No support, stretching management too far, no work life balance"}], [{"review_title": "Nightmare", "rating": "1.0", "reviewer_affiliation": "Current Employee, more than 3 years", "job_date": "28 Feb 2017", "job_title": "Sales Professional in Tallahassee, FL", "duration": "N/A", "pros": "free cable, internet, phone and home security", "cons": "customers and employees are treated like trash"}, {"review_title": "inbound bilingual sales", "rating": "1.0", "reviewer_affiliation": "Former Employee", "job_date": "20 Apr 2018", "job_title": "Anonymous Employee", "duration": "N/A", "pros": "It's a job for someone who is desperate", "cons": "they overwork you for little pay"}, {"review_title": "Comcast - No No", "rating": "1.0", "reviewer_affiliation": "Current Employee, more than 1 year", "job_date": "10 Jan 2019", "job_title": "Anonymous Employee", "duration": "N/A", "pros": "If you can sell, you will make good money.", "cons": "management like to micromanage"}, {"review_title": "worse sales job ever", "rating": "1.0", "reviewer_affiliation": "Former Employee, more than 1 year", "job_date": "5 Apr 2020", "job_title": "Business Account Executive in San Jose, CA", "duration": "N/A", "pros": "none the leadership is a scam", "cons": "there is extreme favortisim, the leadership must change"}, {"review_title": "Short term career.", "rating": "1.0", "reviewer_affiliation": "Former Employee", "job_date": "N/A", "job_title": "N/A", "duration": "N/A", "pros": "Always hiring, esp in sales dept", "cons": "Horrible management, cut throat environment."}, {"review_title": "Warehouse", "rating": "1.0", "reviewer_affiliation": "Former Employee", "job_date": "8 Jul 2015", "job_title": "Warehouse in Schaumburg, IL", "duration": "N/A", "pros": "Friendly management that made a good working environment", "cons": "Horrible service and poor culture"}, {"review_title": "Retail Sales Consultant", "rating": "1.0", "reviewer_affiliation": "Current Employee", "job_date": "28 Nov 2015", "job_title": "Retail Sales Consultant in San Jose, CA", "duration": "N/A", "pros": "Discounted Comcast services. Flex time.", "cons": "Open 7 days a week, no family time."}, {"review_title": "Customer Service", "rating": "1.0", "reviewer_affiliation": "Former Employee, less than 1 year", "job_date": "15 Dec 2015", "job_title": "Call Center Representative in Acworth, GA", "duration": "N/A", "pros": "Horrible company to work for!", "cons": "The pay was HORRIBLE and the hours were Crazy!"}, {"review_title": "Comcast Tech", "rating": "1.0", "reviewer_affiliation": "Former Employee", "job_date": "15 Feb 2017", "job_title": "Anonymous Employee", "duration": "N/A", "pros": "None, its comcast so it sucks", "cons": "It's comcast, so it really sucks a whole bunch"}, {"review_title": "Lifeguard at VB", "rating": "1.0", "reviewer_affiliation": "Former Employee, less than 1 year", "job_date": "10 Apr 2018", "job_title": "Anonymous Employee", "duration": "N/A", "pros": "The benefits package is great", "cons": "The leadership is absolutely terrible at the theme parks."}], [{"review_title": "Analyst 2", "rating": "1.0", "reviewer_affiliation": "Former Employee", "job_date": "30 Aug 2018", "job_title": "Anonymous Employee", "duration": "N/A", "pros": "The benefits are really good.", "cons": "The company has a culture that doesnt breed growth"}, {"review_title": "Customer service", "rating": "1.0", "reviewer_affiliation": "Current Employee, less than 1 year", "job_date": "12 Dec 2018", "job_title": "Customer Service in Denver, CO", "duration": "N/A", "pros": "Good benefits that is about it", "cons": "Management and how they treat their employees"}, {"review_title": "Okay as a parttime employee", "rating": "1.0", "reviewer_affiliation": "Current Employee, less than 1 year", "job_date": "N/A", "job_title": "N/A", "duration": "N/A", "pros": "Hours are good for a student", "cons": "Calling random people all day long"}, {"review_title": "Customer Service Rep", "rating": "1.0", "reviewer_affiliation": "Former Employee, less than 1 year", "job_date": "11 Jul 2019", "job_title": "Customer Service Representative", "duration": "N/A", "pros": "Free Cable, Free Cable, Free Cable", "cons": "Bad hours, Low pay, dealing with angry customers"}, {"review_title": "worst place to work!", "rating": "1.0", "reviewer_affiliation": "Former Employee, more than 3 years", "job_date": "29 Feb 2020", "job_title": "Retention Representative in Silver Spring, MD", "duration": "N/A", "pros": "discount on cable services and fun coworkers", "cons": "everything else no positives at all"}, {"review_title": "BAE", "rating": "1.0", "reviewer_affiliation": "Former Employee, more than 1 year", "job_date": "30 Oct 2014", "job_title": "Anonymous Employee", "duration": "N/A", "pros": "NONE, treat people horribly (customers & employees).", "cons": "They Churn and Burn people."}, {"review_title": "Sales agent", "rating": "1.0", "reviewer_affiliation": "Current Employee, less than 1 year", "job_date": "13 Jun 2015", "job_title": "Inbound Sales Representative in Miramar, FL", "duration": "N/A", "pros": "The schedule were not that bad", "cons": "The metrics for the comissions were horrible"}, {"review_title": "Rep", "rating": "1.0", "reviewer_affiliation": "Former Employee, more than 1 year", "job_date": "3 Aug 2015", "job_title": "Central Division Representative in Marietta, GA", "duration": "N/A", "pros": "part time hours are good", "cons": "sales team markets not good"}, {"review_title": "CAE", "rating": "1.0", "reviewer_affiliation": "Former Employee", "job_date": "N/A", "job_title": "N/A", "duration": "N/A", "pros": "Benefits and interacting with other coworkers.", "cons": "inconstancy  with updating employee regarding policy updates."}, {"review_title": "Comcast Sales", "rating": "1.0", "reviewer_affiliation": "Former Employee, more than 1 year", "job_date": "9 Nov 2016", "job_title": "Direct Sales Representative in Plymouth Meeting, PA", "duration": "N/A", "pros": "Not making quota could place the job at risk.", "cons": "Great commissions and excellent pay"}], [{"review_title": "DONT DO IT!!!!!!", "rating": "1.0", "reviewer_affiliation": "Former Employee, less than 1 year", "job_date": "10 Feb 2017", "job_title": "Anonymous Employee in Philadelphia, PA", "duration": "N/A", "pros": "Flexible work schedule and hours", "cons": "Horrible mamagement don't waste your time"}, {"review_title": "Tech", "rating": "1.0", "reviewer_affiliation": "Former Employee, more than 1 year", "job_date": "12 Oct 2017", "job_title": "Tech in Elmhurst, IL", "duration": "N/A", "pros": "Benefits  and pay is okay", "cons": "Fire u because of an Accident really"}, {"review_title": "Warehouse", "rating": "1.0", "reviewer_affiliation": "Former Employee", "job_date": "1 Feb 2018", "job_title": "Anonymous Employee", "duration": "N/A", "pros": "Good Benefits.  Great Coworkers", "cons": "Bonus system used is extremely unfair.  Poor training."}, {"review_title": "Waste of time", "rating": "1.0", "reviewer_affiliation": "Former Employee", "job_date": "29 Sept 2018", "job_title": "Anonymous Employee", "duration": "N/A", "pros": "Friendly coworkers, nice new location.", "cons": "Management doesn't know how to support their employees."}, {"review_title": "Ok money", "rating": "1.0", "reviewer_affiliation": "Current Employee", "job_date": "6 Oct 2018", "job_title": "Anonymous Employee", "duration": "N/A", "pros": "Good benefits and ok incentive", "cons": "Lack of professionalism and Poor management"}, {"review_title": "Customer account", "rating": "1.0", "reviewer_affiliation": "Former Employee", "job_date": "21 Oct 2018", "job_title": "Anonymous Employee", "duration": "N/A", "pros": "A job with benefits and money", "cons": "Everything else that is bad lack of management"}, {"review_title": "Sales", "rating": "1.0", "reviewer_affiliation": "Current Employee", "job_date": "N/A", "job_title": "N/A", "duration": "N/A", "pros": "Have Great discounts on services.", "cons": "Pay sucks and all the time cutting jobs."}, {"review_title": "downhill", "rating": "1.0", "reviewer_affiliation": "Former Employee, more than 10 years", "job_date": "30 Jun 2015", "job_title": "Comm Tech IV", "duration": "N/A", "pros": "perks, van, discounted services, pay", "cons": "micromanagement, hostile work environment, stressful"}, {"review_title": "Comcast doesn't care", "rating": "1.0", "reviewer_affiliation": "Former Employee", "job_date": "5 Aug 2016", "job_title": "Anonymous Employee", "duration": "N/A", "pros": "Pay, incentives, commission, and benefits.", "cons": "Cons are absolutely everything else."}, {"review_title": "No good", "rating": "1.0", "reviewer_affiliation": "Former Employee, more than 3 years", "job_date": "7 Aug 2016", "job_title": "Anonymous Employee in Denver, CO", "duration": "N/A", "pros": "The benefits are the only good thing.", "cons": "Horrible management. Please fix this."}], [{"review_title": "Management", "rating": "1.0", "reviewer_affiliation": "Former Employee, more than 5 years", "job_date": "7 Sept 2016", "job_title": "Comm Tech IV in Augusta, GA", "duration": "N/A", "pros": "Self-management, Work life balance, Tuition reimbursement", "cons": "Management, Pay, Discrimination, Workload, culture"}, {"review_title": "EAE", "rating": "1.0", "reviewer_affiliation": "Former Employee", "job_date": "19 Jul 2017", "job_title": "Anonymous Employee", "duration": "N/A", "pros": "It has salary and medical benefits", "cons": "The culture does not have room for innovation"}, {"review_title": "Dispatch", "rating": "1.0", "reviewer_affiliation": "Former Employee", "job_date": "18 Sept 2017", "job_title": "Anonymous Employee", "duration": "N/A", "pros": "it was close to home", "cons": "favoritism and always being lied to by management"}, {"review_title": "Decent place to work", "rating": "1.0", "reviewer_affiliation": "Current Employee", "job_date": "5 Feb 2018", "job_title": "Anonymous Employee", "duration": "N/A", "pros": "Good benefits and the pay", "cons": "Interview process took about a month"}, {"review_title": "Tech", "rating": "1.0", "reviewer_affiliation": "Former Employee", "job_date": "N/A", "job_title": "N/A", "duration": "N/A", "pros": "Good money made good friends", "cons": "Terrible management terrible hours impossible deadlines"}, {"review_title": "ok job", "rating": "1.0", "reviewer_affiliation": "Current Employee", "job_date": "N/A", "job_title": "N/A", "duration": "N/A", "pros": "free food and decent pay", "cons": "too much politics and promotion is very limited"}, {"review_title": "Just no.....", "rating": "1.0", "reviewer_affiliation": "Former Employee", "job_date": "N/A", "job_title": "N/A", "duration": "N/A", "pros": "There are no pros here", "cons": "Everything is a con...  Ugh..."}, {"review_title": "BAE 1", "rating": "1.0", "reviewer_affiliation": "Former Employee, more than 1 year", "job_date": "7 Jul 2018", "job_title": "BAE I in Manassas, VA", "duration": "N/A", "pros": "Free cable services for your household", "cons": "Commissions change all the time"}, {"review_title": "Not good", "rating": "1.0", "reviewer_affiliation": "Former Employee, more than 3 years", "job_date": "12 Apr 2019", "job_title": "Sales Representative in Alpharetta, GA", "duration": "N/A", "pros": "Non nothing nice to say", "cons": "They use you a lot and don\u2019t care"}, {"review_title": "Corporate job with corporate mentality", "rating": "1.0", "reviewer_affiliation": "Former Employee, more than 8 years", "job_date": "24 Aug 2019", "job_title": "Sales Project Manager in Seattle, WA", "duration": "N/A", "pros": "benefits, free cable, internet, phone", "cons": "Department closures, horrible customer service"}], [{"review_title": "No room for growth", "rating": "1.0", "reviewer_affiliation": "Former Employee", "job_date": "23 Oct 2019", "job_title": "Escalation Specialist", "duration": "N/A", "pros": "free cable when you start", "cons": "not enough to live off of"}, {"review_title": "Bad", "rating": "1.0", "reviewer_affiliation": "Current Employee", "job_date": "19 Feb 2020", "job_title": "Mechanic", "duration": "N/A", "pros": "Okay pay. They pay for the company car", "cons": "Long hours, need more breaks"}, {"review_title": "customer service/call center", "rating": "1.0", "reviewer_affiliation": "Former Employee", "job_date": "N/A", "job_title": "N/A", "duration": "N/A", "pros": "good benefits, flexible schedule, decent pay", "cons": "everything, horrible management, unrealistic goals"}, {"review_title": "Comcast", "rating": "1.0", "reviewer_affiliation": "Former Employee, more than 1 year", "job_date": "9 Dec 2016", "job_title": "Anonymous Employee in Aurora, CO", "duration": "N/A", "pros": "Great Benefits and cable discounts", "cons": "Comcast HQ makes terrible decisions when hiring leadership"}, {"review_title": "Manager", "rating": "1.0", "reviewer_affiliation": "Former Employee", "job_date": "N/A", "job_title": "N/A", "duration": "N/A", "pros": "Good pay, good benefits, cool technology", "cons": "unethical senior leadership, poor work life balance,"}, {"review_title": "Technical Support Specialist", "rating": "1.0", "reviewer_affiliation": "Former Employee, more than 10 years", "job_date": "31 Jul 2017", "job_title": "Anonymous Employee", "duration": "N/A", "pros": "was the face of the company", "cons": "not a flexible work schedule"}, {"review_title": "Billing Rep", "rating": "1.0", "reviewer_affiliation": "Former Employee, more than 1 year", "job_date": "2 Jan 2019", "job_title": "Anonymous Employee in Saint Paul, MN", "duration": "N/A", "pros": "Pay and the help of others", "cons": "No life and no holidays off"}, {"review_title": "Okay experience", "rating": "1.0", "reviewer_affiliation": "Former Employee", "job_date": "12 Sept 2019", "job_title": "Tech Support Representative", "duration": "N/A", "pros": "Offered overtime which was nice", "cons": "Very stressful calls and not enough support"}, {"review_title": "Was a great company", "rating": "1.0", "reviewer_affiliation": "Current Employee, more than 10 years", "job_date": "31 Dec 2019", "job_title": "Customer Service Representative in Lebanon, PA", "duration": "N/A", "pros": "Great benefits great people", "cons": "Bad management. Hard numbers to meet"}, {"review_title": "Account Executive", "rating": "1.0", "reviewer_affiliation": "Former Employee", "job_date": "N/A", "job_title": "N/A", "duration": "N/A", "pros": "Good pay and flexible hours", "cons": "Poor management unreasonable quota attainment"}], [{"review_title": "Terrible", "rating": "1.0", "reviewer_affiliation": "Former Employee", "job_date": "30 Oct 2014", "job_title": "Anonymous", "duration": "N/A", "pros": "Free cable and Internet services", "cons": "Poor training and useless supervisors"}, {"review_title": "Good temporary job", "rating": "1.0", "reviewer_affiliation": "Current Employee", "job_date": "18 Aug 2015", "job_title": "Anonymous Employee", "duration": "N/A", "pros": "Great benefits, great vacation time", "cons": "low pay, no steady schedule"}, {"review_title": "Good Luck", "rating": "1.0", "reviewer_affiliation": "Former Employee, more than 10 years", "job_date": "26 Aug 2015", "job_title": " in Ormond Beach, FL", "duration": "N/A", "pros": "medical and dental benefits are ok", "cons": "there is no work/life balance"}, {"review_title": "coordinator", "rating": "1.0", "reviewer_affiliation": "Former Employee", "job_date": "N/A", "job_title": "N/A", "duration": "N/A", "pros": "The benefits were really good", "cons": "Overworked & underpaid.  Upper management heavy"}, {"review_title": "AccountManager", "rating": "1.0", "reviewer_affiliation": "Former Employee, more than 1 year", "job_date": "14 Apr 2017", "job_title": "Enterprise Account Manager in Philadelphia, PA", "duration": "N/A", "pros": "There is nothing good about eorking there", "cons": "Everything is subpar Poor management"}, {"review_title": "Sales Developing Manager", "rating": "1.0", "reviewer_affiliation": "Former Employee, less than 1 year", "job_date": "20 Oct 2017", "job_title": "Anonymous Employee", "duration": "N/A", "pros": "Great benefits  quality sales team", "cons": "No communication between departments"}, {"review_title": "Customer service Rep", "rating": "1.0", "reviewer_affiliation": "Current Employee", "job_date": "10 Mar 2020", "job_title": "Customer Service Representative in Fairhaven, MA", "duration": "N/A", "pros": "Discounted cable and paid time off", "cons": "Don\u2019t treat employees well"}, {"review_title": "Comcast", "rating": "1.0", "reviewer_affiliation": "Former Employee, more than 1 year", "job_date": "9 May 2015", "job_title": "Consultant in Beaverton, OR", "duration": "N/A", "pros": "Free Cable service and Internet", "cons": "No Future in the company"}, {"review_title": "Great job", "rating": "1.0", "reviewer_affiliation": "Former Employee", "job_date": "N/A", "job_title": "N/A", "duration": "N/A", "pros": "Great hours and work environment", "cons": "I wish they paid more"}, {"review_title": "csr", "rating": "1.0", "reviewer_affiliation": "Former Employee, more than 1 year", "job_date": "22 Jun 2016", "job_title": "Customer Account Executive/Retention Specialist in Sterling Heights, MI", "duration": "N/A", "pros": "no pros sorry to say", "cons": "nothing good only negative stuff"}], [{"review_title": "Ok company", "rating": "1.0", "reviewer_affiliation": "Current Employee", "job_date": "N/A", "job_title": "N/A", "duration": "N/A", "pros": "Nice benefits\r\nNice people\r\nGreat services\r\nNice workout", "cons": "Horrible pay\r\n Too much work\r\nUnorganized"}, {"review_title": "Project Manager", "rating": "1.0", "reviewer_affiliation": "Current Employee", "job_date": "10 Jul 2017", "job_title": "Anonymous Employee", "duration": "N/A", "pros": "They offer really good benefits", "cons": "They offer really low wages"}, {"review_title": "Customer act execute", "rating": "1.0", "reviewer_affiliation": "Former Employee", "job_date": "9 Sept 2017", "job_title": "Anonymous Employee", "duration": "N/A", "pros": "Nothing horrible place to work", "cons": "Horrible place to work"}, {"review_title": "hg;odsafg", "rating": "1.0", "reviewer_affiliation": "Former Employee", "job_date": "1 Nov 2017", "job_title": "Anonymous Employee", "duration": "N/A", "pros": "pay good people are bad", "cons": "people are bad who call in"}, {"review_title": "No Comment", "rating": "1.0", "reviewer_affiliation": "Former Employee", "job_date": "19 Dec 2017", "job_title": "Anonymous Employee", "duration": "N/A", "pros": "Good Benefits package and perks", "cons": "No comment on this subject"}, {"review_title": "Sales", "rating": "1.0", "reviewer_affiliation": "Former Employee, more than 3 years", "job_date": "15 Oct 2018", "job_title": "Anonymous Employee in Philadelphia, PA", "duration": "N/A", "pros": "Large company with deep pockets.", "cons": "Management is out of touch."}, {"review_title": "Bad", "rating": "1.0", "reviewer_affiliation": "Current Employee", "job_date": "N/A", "job_title": "N/A", "duration": "N/A", "pros": "Bad. Not good. Quite bad.", "cons": "Very bad. Not good. Quite bad."}, {"review_title": "Review", "rating": "1.0", "reviewer_affiliation": "Current Employee, more than 5 years", "job_date": "26 Dec 2016", "job_title": "Network Technician IV in Memphis, TN", "duration": "N/A", "pros": "Place of employment is alright", "cons": "More pay would be nice"}, {"review_title": "sales", "rating": "1.0", "reviewer_affiliation": "Former Employee, less than 1 year", "job_date": "6 Feb 2018", "job_title": "Sales Representative B2B in Denver, CO", "duration": "N/A", "pros": "good benefits, good location", "cons": "Micromanagement , horrible managers"}, {"review_title": "Sales", "rating": "1.0", "reviewer_affiliation": "Current Employee", "job_date": "18 May 2019", "job_title": "Sales in New Castle, DE", "duration": "N/A", "pros": "The money was really great.", "cons": "There really were no cons."}], [{"review_title": "Retention", "rating": "1.0", "reviewer_affiliation": "Former Employee", "job_date": "29 Mar 2017", "job_title": "Anonymous Employee", "duration": "N/A", "pros": "Money money money money money", "cons": "Micromanaging, high turn over"}]]